{
    "Layer_1_Conv2d_3to64": {
        "Filter_0": 178.51,
        "Filter_1": 173.72,
        "Filter_2": 123.22,
        "Filter_3": 127.89,
        "Filter_4": 190.35,
        "Filter_5": 98.99,
        "Filter_6": 157.91,
        "Filter_7": 93.7,
        "Filter_8": 144.78,
        "Filter_9": 94.23,
        "Filter_10": 186.26,
        "Filter_11": 176.83,
        "Filter_12": 170.64,
        "Filter_13": 190.1,
        "Filter_14": 174.63,
        "Filter_15": 183.69,
        "Filter_16": 140.92,
        "Filter_17": 168.73,
        "Filter_18": 143.29,
        "Filter_19": 139.83,
        "Filter_20": 153.02,
        "Filter_21": 189.14,
        "Filter_22": 190.28,
        "Filter_23": 146.24,
        "Filter_24": 190.15,
        "Filter_25": 105.92,
        "Filter_26": 134.4,
        "Filter_27": 153.81,
        "Filter_28": 140.3,
        "Filter_29": 148.61,
        "Filter_30": 187.21,
        "Filter_31": 150.13,
        "Filter_32": 162.64,
        "Filter_33": 127.62,
        "Filter_34": 181.5,
        "Filter_35": 127.86,
        "Filter_36": 165.94,
        "Filter_37": 189.28,
        "Filter_38": 149.21,
        "Filter_39": 174.91,
        "Filter_40": 98.95,
        "Filter_41": 125.13,
        "Filter_42": 184.81,
        "Filter_43": 146.23,
        "Filter_44": 183.04,
        "Filter_45": 148.84,
        "Filter_46": 179.54,
        "Filter_47": 139.74,
        "Filter_48": 160.1,
        "Filter_49": 190.36,
        "Filter_50": 161.08,
        "Filter_51": 182.32,
        "Filter_52": 175.39,
        "Filter_53": 189.17,
        "Filter_54": 134.11,
        "Filter_55": 162.04,
        "Filter_56": 160.31,
        "Filter_57": 141.06,
        "Filter_58": 171.89,
        "Filter_59": 173.58,
        "Filter_60": 151.8,
        "Filter_61": 132.58,
        "Filter_62": 154.13,
        "Filter_63": 190.38
    },
    "Layer_2_Conv2d_64to128": {
        "Filter_0": 111.42,
        "Filter_1": 110.45,
        "Filter_2": 111.48,
        "Filter_3": 111.2,
        "Filter_4": 111.61,
        "Filter_5": 111.86,
        "Filter_6": 111.48,
        "Filter_7": 111.02,
        "Filter_8": 109.1,
        "Filter_9": 111.68,
        "Filter_10": 109.44,
        "Filter_11": 111.09,
        "Filter_12": 110.18,
        "Filter_13": 111.31,
        "Filter_14": 106.05,
        "Filter_15": 101.96,
        "Filter_16": 108.0,
        "Filter_17": 106.88,
        "Filter_18": 110.47,
        "Filter_19": 109.66,
        "Filter_20": 111.05,
        "Filter_21": 111.2,
        "Filter_22": 111.23,
        "Filter_23": 111.16,
        "Filter_24": 109.43,
        "Filter_25": 106.58,
        "Filter_26": 109.99,
        "Filter_27": 110.92,
        "Filter_28": 109.36,
        "Filter_29": 109.58,
        "Filter_30": 111.2,
        "Filter_31": 110.76,
        "Filter_32": 111.22,
        "Filter_33": 110.08,
        "Filter_34": 111.69,
        "Filter_35": 110.96,
        "Filter_36": 105.63,
        "Filter_37": 110.74,
        "Filter_38": 108.38,
        "Filter_39": 108.82,
        "Filter_40": 110.97,
        "Filter_41": 111.14,
        "Filter_42": 111.4,
        "Filter_43": 111.09,
        "Filter_44": 111.32,
        "Filter_45": 111.36,
        "Filter_46": 110.66,
        "Filter_47": 110.68,
        "Filter_48": 110.31,
        "Filter_49": 111.0,
        "Filter_50": 111.61,
        "Filter_51": 109.64,
        "Filter_52": 108.24,
        "Filter_53": 111.61,
        "Filter_54": 111.37,
        "Filter_55": 108.96,
        "Filter_56": 111.68,
        "Filter_57": 102.6,
        "Filter_58": 106.5,
        "Filter_59": 111.65,
        "Filter_60": 110.8,
        "Filter_61": 111.13,
        "Filter_62": 110.3,
        "Filter_63": 107.87,
        "Filter_64": 111.72,
        "Filter_65": 110.86,
        "Filter_66": 110.86,
        "Filter_67": 109.4,
        "Filter_68": 111.52,
        "Filter_69": 110.42,
        "Filter_70": 111.08,
        "Filter_71": 111.14,
        "Filter_72": 110.18,
        "Filter_73": 108.83,
        "Filter_74": 104.14,
        "Filter_75": 111.29,
        "Filter_76": 111.52,
        "Filter_77": 110.21,
        "Filter_78": 109.59,
        "Filter_79": 104.04,
        "Filter_80": 109.64,
        "Filter_81": 111.46,
        "Filter_82": 110.13,
        "Filter_83": 110.32,
        "Filter_84": 108.71,
        "Filter_85": 111.68,
        "Filter_86": 109.72,
        "Filter_87": 111.06,
        "Filter_88": 111.28,
        "Filter_89": 110.79,
        "Filter_90": 110.46,
        "Filter_91": 111.04,
        "Filter_92": 111.46,
        "Filter_93": 108.91,
        "Filter_94": 111.26,
        "Filter_95": 107.9,
        "Filter_96": 109.74,
        "Filter_97": 111.22,
        "Filter_98": 111.13,
        "Filter_99": 110.47,
        "Filter_100": 111.11,
        "Filter_101": 109.76,
        "Filter_102": 110.41,
        "Filter_103": 108.65,
        "Filter_104": 111.64,
        "Filter_105": 106.4,
        "Filter_106": 108.64,
        "Filter_107": 111.64,
        "Filter_108": 110.52,
        "Filter_109": 110.85,
        "Filter_110": 110.16,
        "Filter_111": 109.42,
        "Filter_112": 110.62,
        "Filter_113": 110.93,
        "Filter_114": 111.8,
        "Filter_115": 111.34,
        "Filter_116": 108.15,
        "Filter_117": 110.72,
        "Filter_118": 111.44,
        "Filter_119": 111.3,
        "Filter_120": 109.79,
        "Filter_121": 104.46,
        "Filter_122": 111.21,
        "Filter_123": 109.55,
        "Filter_124": 110.34,
        "Filter_125": 110.45,
        "Filter_126": 108.17,
        "Filter_127": 110.26
    },
    "Layer_3_Conv2d_128to256": {
        "Filter_0": 55.92,
        "Filter_1": 55.96,
        "Filter_2": 55.84,
        "Filter_3": 55.85,
        "Filter_4": 55.78,
        "Filter_5": 55.75,
        "Filter_6": 55.94,
        "Filter_7": 55.84,
        "Filter_8": 55.92,
        "Filter_9": 54.93,
        "Filter_10": 55.85,
        "Filter_11": 55.95,
        "Filter_12": 55.91,
        "Filter_13": 55.99,
        "Filter_14": 55.96,
        "Filter_15": 55.84,
        "Filter_16": 55.93,
        "Filter_17": 55.87,
        "Filter_18": 55.92,
        "Filter_19": 55.99,
        "Filter_20": 55.9,
        "Filter_21": 55.98,
        "Filter_22": 55.92,
        "Filter_23": 55.8,
        "Filter_24": 55.98,
        "Filter_25": 55.84,
        "Filter_26": 55.72,
        "Filter_27": 55.93,
        "Filter_28": 55.77,
        "Filter_29": 55.44,
        "Filter_30": 55.84,
        "Filter_31": 55.81,
        "Filter_32": 55.9,
        "Filter_33": 55.92,
        "Filter_34": 55.87,
        "Filter_35": 56.0,
        "Filter_36": 55.88,
        "Filter_37": 55.91,
        "Filter_38": 55.94,
        "Filter_39": 55.9,
        "Filter_40": 55.97,
        "Filter_41": 55.94,
        "Filter_42": 55.99,
        "Filter_43": 55.92,
        "Filter_44": 55.95,
        "Filter_45": 55.72,
        "Filter_46": 55.92,
        "Filter_47": 55.96,
        "Filter_48": 55.92,
        "Filter_49": 55.95,
        "Filter_50": 55.93,
        "Filter_51": 55.91,
        "Filter_52": 55.94,
        "Filter_53": 55.97,
        "Filter_54": 55.9,
        "Filter_55": 55.95,
        "Filter_56": 55.87,
        "Filter_57": 55.97,
        "Filter_58": 55.07,
        "Filter_59": 55.97,
        "Filter_60": 55.92,
        "Filter_61": 55.93,
        "Filter_62": 55.96,
        "Filter_63": 55.9,
        "Filter_64": 55.45,
        "Filter_65": 55.88,
        "Filter_66": 55.7,
        "Filter_67": 55.97,
        "Filter_68": 55.79,
        "Filter_69": 55.72,
        "Filter_70": 55.76,
        "Filter_71": 55.96,
        "Filter_72": 55.98,
        "Filter_73": 55.95,
        "Filter_74": 55.94,
        "Filter_75": 55.96,
        "Filter_76": 56.0,
        "Filter_77": 55.96,
        "Filter_78": 55.98,
        "Filter_79": 55.92,
        "Filter_80": 55.96,
        "Filter_81": 55.94,
        "Filter_82": 55.94,
        "Filter_83": 55.81,
        "Filter_84": 55.8,
        "Filter_85": 55.8,
        "Filter_86": 55.82,
        "Filter_87": 55.81,
        "Filter_88": 55.85,
        "Filter_89": 55.94,
        "Filter_90": 55.88,
        "Filter_91": 55.92,
        "Filter_92": 55.94,
        "Filter_93": 55.96,
        "Filter_94": 55.89,
        "Filter_95": 55.93,
        "Filter_96": 55.97,
        "Filter_97": 55.8,
        "Filter_98": 55.93,
        "Filter_99": 55.75,
        "Filter_100": 55.96,
        "Filter_101": 55.95,
        "Filter_102": 55.89,
        "Filter_103": 55.95,
        "Filter_104": 55.92,
        "Filter_105": 55.94,
        "Filter_106": 55.77,
        "Filter_107": 55.97,
        "Filter_108": 55.62,
        "Filter_109": 55.9,
        "Filter_110": 55.77,
        "Filter_111": 55.94,
        "Filter_112": 55.81,
        "Filter_113": 55.83,
        "Filter_114": 55.71,
        "Filter_115": 55.98,
        "Filter_116": 55.94,
        "Filter_117": 55.93,
        "Filter_118": 55.89,
        "Filter_119": 55.95,
        "Filter_120": 55.94,
        "Filter_121": 55.89,
        "Filter_122": 56.0,
        "Filter_123": 55.93,
        "Filter_124": 55.97,
        "Filter_125": 55.94,
        "Filter_126": 55.9,
        "Filter_127": 55.74,
        "Filter_128": 55.93,
        "Filter_129": 55.87,
        "Filter_130": 55.87,
        "Filter_131": 55.85,
        "Filter_132": 55.98,
        "Filter_133": 55.93,
        "Filter_134": 55.95,
        "Filter_135": 55.71,
        "Filter_136": 55.97,
        "Filter_137": 55.97,
        "Filter_138": 55.85,
        "Filter_139": 55.92,
        "Filter_140": 55.89,
        "Filter_141": 55.24,
        "Filter_142": 55.97,
        "Filter_143": 55.94,
        "Filter_144": 55.94,
        "Filter_145": 55.93,
        "Filter_146": 55.94,
        "Filter_147": 55.76,
        "Filter_148": 55.7,
        "Filter_149": 55.93,
        "Filter_150": 55.91,
        "Filter_151": 55.65,
        "Filter_152": 55.96,
        "Filter_153": 55.92,
        "Filter_154": 55.78,
        "Filter_155": 55.86,
        "Filter_156": 55.94,
        "Filter_157": 56.0,
        "Filter_158": 55.47,
        "Filter_159": 55.86,
        "Filter_160": 55.94,
        "Filter_161": 55.94,
        "Filter_162": 55.92,
        "Filter_163": 55.92,
        "Filter_164": 55.94,
        "Filter_165": 55.93,
        "Filter_166": 55.91,
        "Filter_167": 55.95,
        "Filter_168": 55.87,
        "Filter_169": 55.95,
        "Filter_170": 55.88,
        "Filter_171": 55.93,
        "Filter_172": 55.91,
        "Filter_173": 55.97,
        "Filter_174": 55.67,
        "Filter_175": 55.0,
        "Filter_176": 55.89,
        "Filter_177": 55.95,
        "Filter_178": 55.97,
        "Filter_179": 55.32,
        "Filter_180": 55.83,
        "Filter_181": 55.86,
        "Filter_182": 55.96,
        "Filter_183": 55.93,
        "Filter_184": 55.8,
        "Filter_185": 55.0,
        "Filter_186": 55.94,
        "Filter_187": 55.83,
        "Filter_188": 55.8,
        "Filter_189": 55.93,
        "Filter_190": 55.87,
        "Filter_191": 55.8,
        "Filter_192": 55.98,
        "Filter_193": 55.83,
        "Filter_194": 55.94,
        "Filter_195": 55.92,
        "Filter_196": 55.9,
        "Filter_197": 55.86,
        "Filter_198": 55.86,
        "Filter_199": 55.98,
        "Filter_200": 55.84,
        "Filter_201": 55.93,
        "Filter_202": 55.89,
        "Filter_203": 55.86,
        "Filter_204": 55.89,
        "Filter_205": 55.82,
        "Filter_206": 55.96,
        "Filter_207": 55.98,
        "Filter_208": 55.9,
        "Filter_209": 55.9,
        "Filter_210": 55.96,
        "Filter_211": 55.58,
        "Filter_212": 55.43,
        "Filter_213": 55.77,
        "Filter_214": 55.95,
        "Filter_215": 55.92,
        "Filter_216": 55.8,
        "Filter_217": 55.92,
        "Filter_218": 55.99,
        "Filter_219": 55.94,
        "Filter_220": 55.89,
        "Filter_221": 55.8,
        "Filter_222": 55.87,
        "Filter_223": 55.91,
        "Filter_224": 55.91,
        "Filter_225": 55.88,
        "Filter_226": 55.92,
        "Filter_227": 55.81,
        "Filter_228": 55.9,
        "Filter_229": 55.77,
        "Filter_230": 55.92,
        "Filter_231": 55.96,
        "Filter_232": 55.92,
        "Filter_233": 55.92,
        "Filter_234": 55.89,
        "Filter_235": 55.91,
        "Filter_236": 55.81,
        "Filter_237": 55.95,
        "Filter_238": 55.85,
        "Filter_239": 55.93,
        "Filter_240": 55.95,
        "Filter_241": 55.76,
        "Filter_242": 55.92,
        "Filter_243": 55.86,
        "Filter_244": 55.82,
        "Filter_245": 55.93,
        "Filter_246": 55.79,
        "Filter_247": 55.93,
        "Filter_248": 55.83,
        "Filter_249": 55.6,
        "Filter_250": 55.88,
        "Filter_251": 55.91,
        "Filter_252": 55.89,
        "Filter_253": 55.91,
        "Filter_254": 55.84,
        "Filter_255": 55.81
    },
    "Layer_4_Conv2d_256to256": {
        "Filter_0": 55.98,
        "Filter_1": 55.91,
        "Filter_2": 55.78,
        "Filter_3": 55.94,
        "Filter_4": 55.96,
        "Filter_5": 55.93,
        "Filter_6": 55.91,
        "Filter_7": 55.95,
        "Filter_8": 55.93,
        "Filter_9": 55.84,
        "Filter_10": 55.96,
        "Filter_11": 55.96,
        "Filter_12": 55.81,
        "Filter_13": 55.87,
        "Filter_14": 55.86,
        "Filter_15": 55.93,
        "Filter_16": 55.88,
        "Filter_17": 55.94,
        "Filter_18": 55.91,
        "Filter_19": 55.96,
        "Filter_20": 55.96,
        "Filter_21": 55.62,
        "Filter_22": 55.94,
        "Filter_23": 55.9,
        "Filter_24": 55.94,
        "Filter_25": 55.81,
        "Filter_26": 55.84,
        "Filter_27": 55.9,
        "Filter_28": 55.94,
        "Filter_29": 55.97,
        "Filter_30": 55.95,
        "Filter_31": 55.98,
        "Filter_32": 55.87,
        "Filter_33": 55.92,
        "Filter_34": 55.99,
        "Filter_35": 55.86,
        "Filter_36": 55.85,
        "Filter_37": 55.98,
        "Filter_38": 55.93,
        "Filter_39": 55.94,
        "Filter_40": 55.9,
        "Filter_41": 55.56,
        "Filter_42": 55.88,
        "Filter_43": 55.98,
        "Filter_44": 55.86,
        "Filter_45": 55.95,
        "Filter_46": 55.98,
        "Filter_47": 55.86,
        "Filter_48": 55.98,
        "Filter_49": 55.95,
        "Filter_50": 55.96,
        "Filter_51": 55.89,
        "Filter_52": 55.96,
        "Filter_53": 55.88,
        "Filter_54": 55.87,
        "Filter_55": 55.84,
        "Filter_56": 55.98,
        "Filter_57": 55.83,
        "Filter_58": 55.89,
        "Filter_59": 56.0,
        "Filter_60": 55.81,
        "Filter_61": 55.97,
        "Filter_62": 55.98,
        "Filter_63": 55.92,
        "Filter_64": 55.91,
        "Filter_65": 55.97,
        "Filter_66": 55.91,
        "Filter_67": 55.9,
        "Filter_68": 55.81,
        "Filter_69": 55.89,
        "Filter_70": 55.9,
        "Filter_71": 55.85,
        "Filter_72": 55.95,
        "Filter_73": 55.81,
        "Filter_74": 55.94,
        "Filter_75": 55.87,
        "Filter_76": 55.88,
        "Filter_77": 55.85,
        "Filter_78": 55.87,
        "Filter_79": 55.93,
        "Filter_80": 55.91,
        "Filter_81": 55.86,
        "Filter_82": 55.82,
        "Filter_83": 55.94,
        "Filter_84": 55.97,
        "Filter_85": 55.86,
        "Filter_86": 55.96,
        "Filter_87": 55.9,
        "Filter_88": 55.93,
        "Filter_89": 55.92,
        "Filter_90": 55.9,
        "Filter_91": 55.91,
        "Filter_92": 55.94,
        "Filter_93": 55.73,
        "Filter_94": 55.93,
        "Filter_95": 55.87,
        "Filter_96": 55.94,
        "Filter_97": 55.96,
        "Filter_98": 55.72,
        "Filter_99": 55.87,
        "Filter_100": 55.9,
        "Filter_101": 55.97,
        "Filter_102": 55.93,
        "Filter_103": 55.88,
        "Filter_104": 55.88,
        "Filter_105": 55.95,
        "Filter_106": 55.84,
        "Filter_107": 55.97,
        "Filter_108": 56.0,
        "Filter_109": 55.83,
        "Filter_110": 55.86,
        "Filter_111": 55.95,
        "Filter_112": 55.9,
        "Filter_113": 55.59,
        "Filter_114": 55.87,
        "Filter_115": 55.97,
        "Filter_116": 55.96,
        "Filter_117": 55.95,
        "Filter_118": 55.96,
        "Filter_119": 55.92,
        "Filter_120": 55.96,
        "Filter_121": 55.88,
        "Filter_122": 56.0,
        "Filter_123": 55.89,
        "Filter_124": 55.97,
        "Filter_125": 55.91,
        "Filter_126": 55.94,
        "Filter_127": 55.77,
        "Filter_128": 55.93,
        "Filter_129": 55.91,
        "Filter_130": 55.94,
        "Filter_131": 55.9,
        "Filter_132": 55.91,
        "Filter_133": 55.94,
        "Filter_134": 55.95,
        "Filter_135": 55.97,
        "Filter_136": 55.87,
        "Filter_137": 55.77,
        "Filter_138": 55.86,
        "Filter_139": 55.9,
        "Filter_140": 55.93,
        "Filter_141": 55.88,
        "Filter_142": 55.9,
        "Filter_143": 55.97,
        "Filter_144": 55.95,
        "Filter_145": 55.96,
        "Filter_146": 55.9,
        "Filter_147": 55.96,
        "Filter_148": 55.77,
        "Filter_149": 55.94,
        "Filter_150": 55.86,
        "Filter_151": 55.85,
        "Filter_152": 55.75,
        "Filter_153": 55.97,
        "Filter_154": 55.8,
        "Filter_155": 55.99,
        "Filter_156": 55.87,
        "Filter_157": 55.98,
        "Filter_158": 55.9,
        "Filter_159": 55.92,
        "Filter_160": 55.95,
        "Filter_161": 55.92,
        "Filter_162": 55.71,
        "Filter_163": 55.91,
        "Filter_164": 55.97,
        "Filter_165": 55.98,
        "Filter_166": 55.88,
        "Filter_167": 55.92,
        "Filter_168": 55.85,
        "Filter_169": 55.87,
        "Filter_170": 55.92,
        "Filter_171": 55.92,
        "Filter_172": 55.99,
        "Filter_173": 55.87,
        "Filter_174": 55.99,
        "Filter_175": 55.94,
        "Filter_176": 55.62,
        "Filter_177": 55.89,
        "Filter_178": 55.93,
        "Filter_179": 55.93,
        "Filter_180": 55.93,
        "Filter_181": 55.9,
        "Filter_182": 55.98,
        "Filter_183": 55.72,
        "Filter_184": 55.99,
        "Filter_185": 55.95,
        "Filter_186": 55.85,
        "Filter_187": 55.86,
        "Filter_188": 55.99,
        "Filter_189": 55.86,
        "Filter_190": 55.98,
        "Filter_191": 55.98,
        "Filter_192": 55.89,
        "Filter_193": 55.97,
        "Filter_194": 55.89,
        "Filter_195": 55.95,
        "Filter_196": 55.91,
        "Filter_197": 55.8,
        "Filter_198": 56.0,
        "Filter_199": 55.87,
        "Filter_200": 55.96,
        "Filter_201": 55.92,
        "Filter_202": 55.93,
        "Filter_203": 55.85,
        "Filter_204": 55.94,
        "Filter_205": 55.87,
        "Filter_206": 55.87,
        "Filter_207": 55.85,
        "Filter_208": 55.75,
        "Filter_209": 55.94,
        "Filter_210": 55.9,
        "Filter_211": 55.97,
        "Filter_212": 55.88,
        "Filter_213": 55.91,
        "Filter_214": 55.86,
        "Filter_215": 55.61,
        "Filter_216": 55.93,
        "Filter_217": 55.94,
        "Filter_218": 55.92,
        "Filter_219": 55.87,
        "Filter_220": 55.99,
        "Filter_221": 55.91,
        "Filter_222": 55.94,
        "Filter_223": 55.9,
        "Filter_224": 56.0,
        "Filter_225": 55.87,
        "Filter_226": 55.88,
        "Filter_227": 55.86,
        "Filter_228": 55.96,
        "Filter_229": 55.9,
        "Filter_230": 55.8,
        "Filter_231": 55.78,
        "Filter_232": 55.98,
        "Filter_233": 55.9,
        "Filter_234": 55.62,
        "Filter_235": 55.96,
        "Filter_236": 55.93,
        "Filter_237": 55.85,
        "Filter_238": 55.87,
        "Filter_239": 55.91,
        "Filter_240": 55.95,
        "Filter_241": 55.98,
        "Filter_242": 55.81,
        "Filter_243": 55.92,
        "Filter_244": 55.92,
        "Filter_245": 55.92,
        "Filter_246": 55.97,
        "Filter_247": 55.86,
        "Filter_248": 55.83,
        "Filter_249": 55.92,
        "Filter_250": 55.99,
        "Filter_251": 55.98,
        "Filter_252": 55.86,
        "Filter_253": 55.99,
        "Filter_254": 55.93,
        "Filter_255": 55.97
    },
    "Layer_5_Conv2d_256to512": {
        "Filter_0": 27.99,
        "Filter_1": 28.0,
        "Filter_2": 28.0,
        "Filter_3": 27.98,
        "Filter_4": 28.0,
        "Filter_5": 28.0,
        "Filter_6": 28.0,
        "Filter_7": 28.0,
        "Filter_8": 27.99,
        "Filter_9": 28.0,
        "Filter_10": 28.0,
        "Filter_11": 28.0,
        "Filter_12": 27.98,
        "Filter_13": 27.98,
        "Filter_14": 28.0,
        "Filter_15": 27.99,
        "Filter_16": 28.0,
        "Filter_17": 28.0,
        "Filter_18": 27.97,
        "Filter_19": 28.0,
        "Filter_20": 27.99,
        "Filter_21": 28.0,
        "Filter_22": 27.98,
        "Filter_23": 27.99,
        "Filter_24": 27.98,
        "Filter_25": 28.0,
        "Filter_26": 28.0,
        "Filter_27": 27.98,
        "Filter_28": 27.99,
        "Filter_29": 28.0,
        "Filter_30": 27.99,
        "Filter_31": 28.0,
        "Filter_32": 28.0,
        "Filter_33": 28.0,
        "Filter_34": 28.0,
        "Filter_35": 27.99,
        "Filter_36": 28.0,
        "Filter_37": 27.99,
        "Filter_38": 28.0,
        "Filter_39": 27.99,
        "Filter_40": 27.99,
        "Filter_41": 28.0,
        "Filter_42": 28.0,
        "Filter_43": 28.0,
        "Filter_44": 28.0,
        "Filter_45": 28.0,
        "Filter_46": 28.0,
        "Filter_47": 28.0,
        "Filter_48": 28.0,
        "Filter_49": 28.0,
        "Filter_50": 28.0,
        "Filter_51": 28.0,
        "Filter_52": 28.0,
        "Filter_53": 28.0,
        "Filter_54": 28.0,
        "Filter_55": 27.99,
        "Filter_56": 27.99,
        "Filter_57": 28.0,
        "Filter_58": 27.98,
        "Filter_59": 28.0,
        "Filter_60": 28.0,
        "Filter_61": 27.99,
        "Filter_62": 28.0,
        "Filter_63": 27.99,
        "Filter_64": 27.99,
        "Filter_65": 27.97,
        "Filter_66": 28.0,
        "Filter_67": 28.0,
        "Filter_68": 28.0,
        "Filter_69": 28.0,
        "Filter_70": 28.0,
        "Filter_71": 28.0,
        "Filter_72": 28.0,
        "Filter_73": 28.0,
        "Filter_74": 27.98,
        "Filter_75": 27.98,
        "Filter_76": 28.0,
        "Filter_77": 28.0,
        "Filter_78": 28.0,
        "Filter_79": 27.97,
        "Filter_80": 28.0,
        "Filter_81": 28.0,
        "Filter_82": 27.99,
        "Filter_83": 28.0,
        "Filter_84": 28.0,
        "Filter_85": 28.0,
        "Filter_86": 28.0,
        "Filter_87": 28.0,
        "Filter_88": 28.0,
        "Filter_89": 28.0,
        "Filter_90": 28.0,
        "Filter_91": 28.0,
        "Filter_92": 27.98,
        "Filter_93": 27.99,
        "Filter_94": 27.97,
        "Filter_95": 27.99,
        "Filter_96": 28.0,
        "Filter_97": 28.0,
        "Filter_98": 28.0,
        "Filter_99": 28.0,
        "Filter_100": 28.0,
        "Filter_101": 28.0,
        "Filter_102": 27.99,
        "Filter_103": 27.99,
        "Filter_104": 28.0,
        "Filter_105": 28.0,
        "Filter_106": 27.99,
        "Filter_107": 27.99,
        "Filter_108": 28.0,
        "Filter_109": 28.0,
        "Filter_110": 28.0,
        "Filter_111": 28.0,
        "Filter_112": 28.0,
        "Filter_113": 28.0,
        "Filter_114": 28.0,
        "Filter_115": 28.0,
        "Filter_116": 28.0,
        "Filter_117": 28.0,
        "Filter_118": 28.0,
        "Filter_119": 28.0,
        "Filter_120": 28.0,
        "Filter_121": 28.0,
        "Filter_122": 28.0,
        "Filter_123": 28.0,
        "Filter_124": 27.99,
        "Filter_125": 28.0,
        "Filter_126": 27.99,
        "Filter_127": 28.0,
        "Filter_128": 28.0,
        "Filter_129": 27.98,
        "Filter_130": 27.99,
        "Filter_131": 27.99,
        "Filter_132": 28.0,
        "Filter_133": 28.0,
        "Filter_134": 28.0,
        "Filter_135": 28.0,
        "Filter_136": 27.99,
        "Filter_137": 28.0,
        "Filter_138": 28.0,
        "Filter_139": 27.99,
        "Filter_140": 28.0,
        "Filter_141": 28.0,
        "Filter_142": 28.0,
        "Filter_143": 28.0,
        "Filter_144": 27.99,
        "Filter_145": 28.0,
        "Filter_146": 28.0,
        "Filter_147": 28.0,
        "Filter_148": 28.0,
        "Filter_149": 28.0,
        "Filter_150": 27.99,
        "Filter_151": 27.98,
        "Filter_152": 27.99,
        "Filter_153": 27.99,
        "Filter_154": 28.0,
        "Filter_155": 27.99,
        "Filter_156": 28.0,
        "Filter_157": 27.98,
        "Filter_158": 27.99,
        "Filter_159": 28.0,
        "Filter_160": 28.0,
        "Filter_161": 28.0,
        "Filter_162": 27.99,
        "Filter_163": 28.0,
        "Filter_164": 27.98,
        "Filter_165": 27.99,
        "Filter_166": 28.0,
        "Filter_167": 27.99,
        "Filter_168": 27.98,
        "Filter_169": 28.0,
        "Filter_170": 28.0,
        "Filter_171": 28.0,
        "Filter_172": 28.0,
        "Filter_173": 27.99,
        "Filter_174": 28.0,
        "Filter_175": 28.0,
        "Filter_176": 28.0,
        "Filter_177": 28.0,
        "Filter_178": 27.99,
        "Filter_179": 28.0,
        "Filter_180": 27.99,
        "Filter_181": 27.99,
        "Filter_182": 28.0,
        "Filter_183": 28.0,
        "Filter_184": 27.99,
        "Filter_185": 28.0,
        "Filter_186": 28.0,
        "Filter_187": 28.0,
        "Filter_188": 27.99,
        "Filter_189": 27.99,
        "Filter_190": 28.0,
        "Filter_191": 28.0,
        "Filter_192": 28.0,
        "Filter_193": 27.98,
        "Filter_194": 28.0,
        "Filter_195": 28.0,
        "Filter_196": 28.0,
        "Filter_197": 28.0,
        "Filter_198": 28.0,
        "Filter_199": 28.0,
        "Filter_200": 27.99,
        "Filter_201": 28.0,
        "Filter_202": 28.0,
        "Filter_203": 27.99,
        "Filter_204": 27.98,
        "Filter_205": 27.99,
        "Filter_206": 28.0,
        "Filter_207": 28.0,
        "Filter_208": 28.0,
        "Filter_209": 28.0,
        "Filter_210": 28.0,
        "Filter_211": 28.0,
        "Filter_212": 27.98,
        "Filter_213": 28.0,
        "Filter_214": 28.0,
        "Filter_215": 27.97,
        "Filter_216": 27.99,
        "Filter_217": 28.0,
        "Filter_218": 27.99,
        "Filter_219": 28.0,
        "Filter_220": 28.0,
        "Filter_221": 28.0,
        "Filter_222": 28.0,
        "Filter_223": 28.0,
        "Filter_224": 27.99,
        "Filter_225": 28.0,
        "Filter_226": 27.99,
        "Filter_227": 28.0,
        "Filter_228": 28.0,
        "Filter_229": 28.0,
        "Filter_230": 28.0,
        "Filter_231": 28.0,
        "Filter_232": 28.0,
        "Filter_233": 28.0,
        "Filter_234": 28.0,
        "Filter_235": 28.0,
        "Filter_236": 28.0,
        "Filter_237": 28.0,
        "Filter_238": 27.99,
        "Filter_239": 28.0,
        "Filter_240": 28.0,
        "Filter_241": 28.0,
        "Filter_242": 28.0,
        "Filter_243": 28.0,
        "Filter_244": 28.0,
        "Filter_245": 28.0,
        "Filter_246": 28.0,
        "Filter_247": 28.0,
        "Filter_248": 28.0,
        "Filter_249": 28.0,
        "Filter_250": 28.0,
        "Filter_251": 27.99,
        "Filter_252": 28.0,
        "Filter_253": 28.0,
        "Filter_254": 28.0,
        "Filter_255": 28.0,
        "Filter_256": 28.0,
        "Filter_257": 28.0,
        "Filter_258": 28.0,
        "Filter_259": 28.0,
        "Filter_260": 28.0,
        "Filter_261": 27.99,
        "Filter_262": 28.0,
        "Filter_263": 28.0,
        "Filter_264": 28.0,
        "Filter_265": 28.0,
        "Filter_266": 27.99,
        "Filter_267": 27.99,
        "Filter_268": 28.0,
        "Filter_269": 28.0,
        "Filter_270": 28.0,
        "Filter_271": 27.99,
        "Filter_272": 27.99,
        "Filter_273": 27.99,
        "Filter_274": 27.99,
        "Filter_275": 27.99,
        "Filter_276": 28.0,
        "Filter_277": 28.0,
        "Filter_278": 28.0,
        "Filter_279": 27.99,
        "Filter_280": 28.0,
        "Filter_281": 28.0,
        "Filter_282": 28.0,
        "Filter_283": 28.0,
        "Filter_284": 27.99,
        "Filter_285": 28.0,
        "Filter_286": 28.0,
        "Filter_287": 28.0,
        "Filter_288": 28.0,
        "Filter_289": 28.0,
        "Filter_290": 27.98,
        "Filter_291": 28.0,
        "Filter_292": 28.0,
        "Filter_293": 27.99,
        "Filter_294": 28.0,
        "Filter_295": 28.0,
        "Filter_296": 28.0,
        "Filter_297": 28.0,
        "Filter_298": 27.99,
        "Filter_299": 28.0,
        "Filter_300": 28.0,
        "Filter_301": 27.99,
        "Filter_302": 28.0,
        "Filter_303": 28.0,
        "Filter_304": 28.0,
        "Filter_305": 28.0,
        "Filter_306": 28.0,
        "Filter_307": 28.0,
        "Filter_308": 27.99,
        "Filter_309": 28.0,
        "Filter_310": 27.99,
        "Filter_311": 28.0,
        "Filter_312": 27.99,
        "Filter_313": 27.99,
        "Filter_314": 28.0,
        "Filter_315": 27.99,
        "Filter_316": 28.0,
        "Filter_317": 28.0,
        "Filter_318": 27.99,
        "Filter_319": 28.0,
        "Filter_320": 28.0,
        "Filter_321": 28.0,
        "Filter_322": 27.98,
        "Filter_323": 28.0,
        "Filter_324": 28.0,
        "Filter_325": 28.0,
        "Filter_326": 28.0,
        "Filter_327": 28.0,
        "Filter_328": 28.0,
        "Filter_329": 28.0,
        "Filter_330": 28.0,
        "Filter_331": 27.99,
        "Filter_332": 27.99,
        "Filter_333": 28.0,
        "Filter_334": 28.0,
        "Filter_335": 28.0,
        "Filter_336": 27.99,
        "Filter_337": 27.99,
        "Filter_338": 27.99,
        "Filter_339": 28.0,
        "Filter_340": 27.99,
        "Filter_341": 28.0,
        "Filter_342": 28.0,
        "Filter_343": 28.0,
        "Filter_344": 28.0,
        "Filter_345": 27.99,
        "Filter_346": 28.0,
        "Filter_347": 28.0,
        "Filter_348": 28.0,
        "Filter_349": 28.0,
        "Filter_350": 27.99,
        "Filter_351": 28.0,
        "Filter_352": 28.0,
        "Filter_353": 27.99,
        "Filter_354": 28.0,
        "Filter_355": 28.0,
        "Filter_356": 27.99,
        "Filter_357": 27.99,
        "Filter_358": 27.98,
        "Filter_359": 28.0,
        "Filter_360": 28.0,
        "Filter_361": 28.0,
        "Filter_362": 27.97,
        "Filter_363": 28.0,
        "Filter_364": 28.0,
        "Filter_365": 28.0,
        "Filter_366": 28.0,
        "Filter_367": 28.0,
        "Filter_368": 28.0,
        "Filter_369": 28.0,
        "Filter_370": 28.0,
        "Filter_371": 28.0,
        "Filter_372": 28.0,
        "Filter_373": 28.0,
        "Filter_374": 27.99,
        "Filter_375": 27.98,
        "Filter_376": 28.0,
        "Filter_377": 28.0,
        "Filter_378": 28.0,
        "Filter_379": 28.0,
        "Filter_380": 28.0,
        "Filter_381": 28.0,
        "Filter_382": 28.0,
        "Filter_383": 27.99,
        "Filter_384": 28.0,
        "Filter_385": 27.98,
        "Filter_386": 28.0,
        "Filter_387": 28.0,
        "Filter_388": 28.0,
        "Filter_389": 27.97,
        "Filter_390": 28.0,
        "Filter_391": 28.0,
        "Filter_392": 28.0,
        "Filter_393": 28.0,
        "Filter_394": 28.0,
        "Filter_395": 27.99,
        "Filter_396": 28.0,
        "Filter_397": 28.0,
        "Filter_398": 27.99,
        "Filter_399": 28.0,
        "Filter_400": 28.0,
        "Filter_401": 27.99,
        "Filter_402": 27.98,
        "Filter_403": 27.99,
        "Filter_404": 28.0,
        "Filter_405": 28.0,
        "Filter_406": 27.99,
        "Filter_407": 27.99,
        "Filter_408": 28.0,
        "Filter_409": 28.0,
        "Filter_410": 27.99,
        "Filter_411": 28.0,
        "Filter_412": 28.0,
        "Filter_413": 28.0,
        "Filter_414": 28.0,
        "Filter_415": 28.0,
        "Filter_416": 28.0,
        "Filter_417": 28.0,
        "Filter_418": 28.0,
        "Filter_419": 28.0,
        "Filter_420": 28.0,
        "Filter_421": 28.0,
        "Filter_422": 27.99,
        "Filter_423": 27.99,
        "Filter_424": 28.0,
        "Filter_425": 28.0,
        "Filter_426": 28.0,
        "Filter_427": 28.0,
        "Filter_428": 28.0,
        "Filter_429": 27.99,
        "Filter_430": 27.99,
        "Filter_431": 28.0,
        "Filter_432": 28.0,
        "Filter_433": 28.0,
        "Filter_434": 28.0,
        "Filter_435": 28.0,
        "Filter_436": 28.0,
        "Filter_437": 28.0,
        "Filter_438": 28.0,
        "Filter_439": 28.0,
        "Filter_440": 27.98,
        "Filter_441": 28.0,
        "Filter_442": 28.0,
        "Filter_443": 27.99,
        "Filter_444": 28.0,
        "Filter_445": 27.99,
        "Filter_446": 28.0,
        "Filter_447": 28.0,
        "Filter_448": 27.99,
        "Filter_449": 27.99,
        "Filter_450": 27.99,
        "Filter_451": 27.98,
        "Filter_452": 27.99,
        "Filter_453": 28.0,
        "Filter_454": 27.99,
        "Filter_455": 28.0,
        "Filter_456": 28.0,
        "Filter_457": 28.0,
        "Filter_458": 28.0,
        "Filter_459": 28.0,
        "Filter_460": 28.0,
        "Filter_461": 28.0,
        "Filter_462": 28.0,
        "Filter_463": 28.0,
        "Filter_464": 28.0,
        "Filter_465": 28.0,
        "Filter_466": 28.0,
        "Filter_467": 28.0,
        "Filter_468": 28.0,
        "Filter_469": 28.0,
        "Filter_470": 27.99,
        "Filter_471": 27.99,
        "Filter_472": 28.0,
        "Filter_473": 28.0,
        "Filter_474": 27.97,
        "Filter_475": 28.0,
        "Filter_476": 28.0,
        "Filter_477": 28.0,
        "Filter_478": 28.0,
        "Filter_479": 28.0,
        "Filter_480": 28.0,
        "Filter_481": 28.0,
        "Filter_482": 27.99,
        "Filter_483": 28.0,
        "Filter_484": 27.99,
        "Filter_485": 28.0,
        "Filter_486": 28.0,
        "Filter_487": 28.0,
        "Filter_488": 28.0,
        "Filter_489": 28.0,
        "Filter_490": 28.0,
        "Filter_491": 28.0,
        "Filter_492": 28.0,
        "Filter_493": 28.0,
        "Filter_494": 28.0,
        "Filter_495": 28.0,
        "Filter_496": 28.0,
        "Filter_497": 28.0,
        "Filter_498": 28.0,
        "Filter_499": 27.97,
        "Filter_500": 27.99,
        "Filter_501": 28.0,
        "Filter_502": 28.0,
        "Filter_503": 28.0,
        "Filter_504": 27.99,
        "Filter_505": 28.0,
        "Filter_506": 27.99,
        "Filter_507": 27.99,
        "Filter_508": 28.0,
        "Filter_509": 28.0,
        "Filter_510": 28.0,
        "Filter_511": 27.99
    },
    "Layer_6_Conv2d_512to512": {
        "Filter_0": 28.0,
        "Filter_1": 27.99,
        "Filter_2": 28.0,
        "Filter_3": 28.0,
        "Filter_4": 27.97,
        "Filter_5": 28.0,
        "Filter_6": 28.0,
        "Filter_7": 28.0,
        "Filter_8": 27.97,
        "Filter_9": 27.99,
        "Filter_10": 27.98,
        "Filter_11": 27.99,
        "Filter_12": 27.97,
        "Filter_13": 27.99,
        "Filter_14": 28.0,
        "Filter_15": 28.0,
        "Filter_16": 28.0,
        "Filter_17": 28.0,
        "Filter_18": 27.98,
        "Filter_19": 28.0,
        "Filter_20": 27.98,
        "Filter_21": 27.99,
        "Filter_22": 27.97,
        "Filter_23": 27.99,
        "Filter_24": 28.0,
        "Filter_25": 27.99,
        "Filter_26": 27.99,
        "Filter_27": 28.0,
        "Filter_28": 27.99,
        "Filter_29": 27.99,
        "Filter_30": 28.0,
        "Filter_31": 27.99,
        "Filter_32": 27.98,
        "Filter_33": 28.0,
        "Filter_34": 27.99,
        "Filter_35": 28.0,
        "Filter_36": 27.99,
        "Filter_37": 28.0,
        "Filter_38": 28.0,
        "Filter_39": 27.99,
        "Filter_40": 27.99,
        "Filter_41": 28.0,
        "Filter_42": 27.99,
        "Filter_43": 28.0,
        "Filter_44": 27.98,
        "Filter_45": 27.99,
        "Filter_46": 27.98,
        "Filter_47": 28.0,
        "Filter_48": 28.0,
        "Filter_49": 28.0,
        "Filter_50": 28.0,
        "Filter_51": 28.0,
        "Filter_52": 28.0,
        "Filter_53": 28.0,
        "Filter_54": 27.99,
        "Filter_55": 27.99,
        "Filter_56": 28.0,
        "Filter_57": 27.99,
        "Filter_58": 27.99,
        "Filter_59": 28.0,
        "Filter_60": 27.99,
        "Filter_61": 27.98,
        "Filter_62": 27.98,
        "Filter_63": 28.0,
        "Filter_64": 28.0,
        "Filter_65": 27.97,
        "Filter_66": 27.99,
        "Filter_67": 28.0,
        "Filter_68": 27.96,
        "Filter_69": 27.99,
        "Filter_70": 28.0,
        "Filter_71": 28.0,
        "Filter_72": 27.99,
        "Filter_73": 27.99,
        "Filter_74": 27.98,
        "Filter_75": 28.0,
        "Filter_76": 28.0,
        "Filter_77": 28.0,
        "Filter_78": 28.0,
        "Filter_79": 28.0,
        "Filter_80": 27.98,
        "Filter_81": 27.99,
        "Filter_82": 28.0,
        "Filter_83": 27.99,
        "Filter_84": 27.99,
        "Filter_85": 28.0,
        "Filter_86": 27.99,
        "Filter_87": 28.0,
        "Filter_88": 27.98,
        "Filter_89": 28.0,
        "Filter_90": 27.99,
        "Filter_91": 27.99,
        "Filter_92": 27.99,
        "Filter_93": 28.0,
        "Filter_94": 28.0,
        "Filter_95": 28.0,
        "Filter_96": 28.0,
        "Filter_97": 27.99,
        "Filter_98": 27.99,
        "Filter_99": 28.0,
        "Filter_100": 27.98,
        "Filter_101": 27.98,
        "Filter_102": 28.0,
        "Filter_103": 28.0,
        "Filter_104": 27.99,
        "Filter_105": 27.98,
        "Filter_106": 27.97,
        "Filter_107": 27.99,
        "Filter_108": 28.0,
        "Filter_109": 28.0,
        "Filter_110": 27.99,
        "Filter_111": 28.0,
        "Filter_112": 28.0,
        "Filter_113": 27.99,
        "Filter_114": 28.0,
        "Filter_115": 28.0,
        "Filter_116": 28.0,
        "Filter_117": 27.98,
        "Filter_118": 27.99,
        "Filter_119": 27.98,
        "Filter_120": 27.99,
        "Filter_121": 27.99,
        "Filter_122": 27.99,
        "Filter_123": 28.0,
        "Filter_124": 27.98,
        "Filter_125": 27.97,
        "Filter_126": 27.99,
        "Filter_127": 27.97,
        "Filter_128": 28.0,
        "Filter_129": 28.0,
        "Filter_130": 27.99,
        "Filter_131": 27.99,
        "Filter_132": 28.0,
        "Filter_133": 27.97,
        "Filter_134": 27.99,
        "Filter_135": 27.98,
        "Filter_136": 28.0,
        "Filter_137": 27.99,
        "Filter_138": 28.0,
        "Filter_139": 28.0,
        "Filter_140": 28.0,
        "Filter_141": 27.98,
        "Filter_142": 27.98,
        "Filter_143": 28.0,
        "Filter_144": 28.0,
        "Filter_145": 27.99,
        "Filter_146": 27.97,
        "Filter_147": 27.99,
        "Filter_148": 27.97,
        "Filter_149": 27.98,
        "Filter_150": 28.0,
        "Filter_151": 27.98,
        "Filter_152": 27.98,
        "Filter_153": 28.0,
        "Filter_154": 27.99,
        "Filter_155": 27.99,
        "Filter_156": 28.0,
        "Filter_157": 27.99,
        "Filter_158": 28.0,
        "Filter_159": 28.0,
        "Filter_160": 27.99,
        "Filter_161": 28.0,
        "Filter_162": 28.0,
        "Filter_163": 27.99,
        "Filter_164": 27.99,
        "Filter_165": 28.0,
        "Filter_166": 28.0,
        "Filter_167": 27.98,
        "Filter_168": 27.98,
        "Filter_169": 28.0,
        "Filter_170": 27.99,
        "Filter_171": 27.98,
        "Filter_172": 28.0,
        "Filter_173": 27.99,
        "Filter_174": 28.0,
        "Filter_175": 27.99,
        "Filter_176": 28.0,
        "Filter_177": 28.0,
        "Filter_178": 27.99,
        "Filter_179": 27.98,
        "Filter_180": 27.99,
        "Filter_181": 27.99,
        "Filter_182": 27.99,
        "Filter_183": 28.0,
        "Filter_184": 27.98,
        "Filter_185": 27.98,
        "Filter_186": 28.0,
        "Filter_187": 28.0,
        "Filter_188": 27.99,
        "Filter_189": 27.99,
        "Filter_190": 27.99,
        "Filter_191": 27.97,
        "Filter_192": 27.98,
        "Filter_193": 27.99,
        "Filter_194": 28.0,
        "Filter_195": 28.0,
        "Filter_196": 27.96,
        "Filter_197": 27.98,
        "Filter_198": 27.97,
        "Filter_199": 27.99,
        "Filter_200": 28.0,
        "Filter_201": 28.0,
        "Filter_202": 27.98,
        "Filter_203": 28.0,
        "Filter_204": 27.99,
        "Filter_205": 27.99,
        "Filter_206": 27.99,
        "Filter_207": 27.97,
        "Filter_208": 27.99,
        "Filter_209": 28.0,
        "Filter_210": 27.98,
        "Filter_211": 28.0,
        "Filter_212": 27.99,
        "Filter_213": 28.0,
        "Filter_214": 28.0,
        "Filter_215": 28.0,
        "Filter_216": 28.0,
        "Filter_217": 27.99,
        "Filter_218": 28.0,
        "Filter_219": 27.97,
        "Filter_220": 27.99,
        "Filter_221": 27.98,
        "Filter_222": 27.98,
        "Filter_223": 27.99,
        "Filter_224": 27.97,
        "Filter_225": 28.0,
        "Filter_226": 27.98,
        "Filter_227": 28.0,
        "Filter_228": 28.0,
        "Filter_229": 28.0,
        "Filter_230": 28.0,
        "Filter_231": 27.99,
        "Filter_232": 27.98,
        "Filter_233": 28.0,
        "Filter_234": 27.97,
        "Filter_235": 27.99,
        "Filter_236": 27.99,
        "Filter_237": 28.0,
        "Filter_238": 27.99,
        "Filter_239": 27.99,
        "Filter_240": 27.99,
        "Filter_241": 28.0,
        "Filter_242": 28.0,
        "Filter_243": 27.99,
        "Filter_244": 28.0,
        "Filter_245": 27.99,
        "Filter_246": 27.99,
        "Filter_247": 28.0,
        "Filter_248": 27.97,
        "Filter_249": 27.99,
        "Filter_250": 27.99,
        "Filter_251": 28.0,
        "Filter_252": 27.98,
        "Filter_253": 28.0,
        "Filter_254": 28.0,
        "Filter_255": 27.99,
        "Filter_256": 28.0,
        "Filter_257": 28.0,
        "Filter_258": 28.0,
        "Filter_259": 27.99,
        "Filter_260": 28.0,
        "Filter_261": 27.99,
        "Filter_262": 27.99,
        "Filter_263": 27.97,
        "Filter_264": 27.99,
        "Filter_265": 27.98,
        "Filter_266": 28.0,
        "Filter_267": 27.97,
        "Filter_268": 27.99,
        "Filter_269": 27.98,
        "Filter_270": 28.0,
        "Filter_271": 27.99,
        "Filter_272": 28.0,
        "Filter_273": 27.99,
        "Filter_274": 28.0,
        "Filter_275": 28.0,
        "Filter_276": 27.99,
        "Filter_277": 27.99,
        "Filter_278": 28.0,
        "Filter_279": 28.0,
        "Filter_280": 27.98,
        "Filter_281": 28.0,
        "Filter_282": 28.0,
        "Filter_283": 28.0,
        "Filter_284": 28.0,
        "Filter_285": 27.98,
        "Filter_286": 27.99,
        "Filter_287": 28.0,
        "Filter_288": 27.99,
        "Filter_289": 28.0,
        "Filter_290": 28.0,
        "Filter_291": 28.0,
        "Filter_292": 28.0,
        "Filter_293": 27.99,
        "Filter_294": 27.99,
        "Filter_295": 27.98,
        "Filter_296": 27.98,
        "Filter_297": 28.0,
        "Filter_298": 27.99,
        "Filter_299": 27.99,
        "Filter_300": 27.98,
        "Filter_301": 27.99,
        "Filter_302": 27.99,
        "Filter_303": 27.99,
        "Filter_304": 28.0,
        "Filter_305": 28.0,
        "Filter_306": 27.99,
        "Filter_307": 28.0,
        "Filter_308": 27.99,
        "Filter_309": 27.98,
        "Filter_310": 28.0,
        "Filter_311": 27.99,
        "Filter_312": 28.0,
        "Filter_313": 28.0,
        "Filter_314": 28.0,
        "Filter_315": 27.98,
        "Filter_316": 27.99,
        "Filter_317": 28.0,
        "Filter_318": 27.99,
        "Filter_319": 27.98,
        "Filter_320": 28.0,
        "Filter_321": 28.0,
        "Filter_322": 27.96,
        "Filter_323": 27.98,
        "Filter_324": 28.0,
        "Filter_325": 27.98,
        "Filter_326": 28.0,
        "Filter_327": 27.99,
        "Filter_328": 28.0,
        "Filter_329": 27.99,
        "Filter_330": 27.98,
        "Filter_331": 28.0,
        "Filter_332": 27.99,
        "Filter_333": 28.0,
        "Filter_334": 27.99,
        "Filter_335": 28.0,
        "Filter_336": 28.0,
        "Filter_337": 28.0,
        "Filter_338": 28.0,
        "Filter_339": 27.97,
        "Filter_340": 27.98,
        "Filter_341": 28.0,
        "Filter_342": 28.0,
        "Filter_343": 28.0,
        "Filter_344": 28.0,
        "Filter_345": 28.0,
        "Filter_346": 27.99,
        "Filter_347": 27.98,
        "Filter_348": 28.0,
        "Filter_349": 28.0,
        "Filter_350": 27.97,
        "Filter_351": 27.98,
        "Filter_352": 28.0,
        "Filter_353": 27.99,
        "Filter_354": 28.0,
        "Filter_355": 28.0,
        "Filter_356": 28.0,
        "Filter_357": 27.99,
        "Filter_358": 28.0,
        "Filter_359": 27.98,
        "Filter_360": 28.0,
        "Filter_361": 28.0,
        "Filter_362": 28.0,
        "Filter_363": 28.0,
        "Filter_364": 28.0,
        "Filter_365": 28.0,
        "Filter_366": 28.0,
        "Filter_367": 27.95,
        "Filter_368": 28.0,
        "Filter_369": 27.99,
        "Filter_370": 27.98,
        "Filter_371": 27.99,
        "Filter_372": 27.99,
        "Filter_373": 28.0,
        "Filter_374": 28.0,
        "Filter_375": 27.99,
        "Filter_376": 28.0,
        "Filter_377": 27.98,
        "Filter_378": 27.98,
        "Filter_379": 28.0,
        "Filter_380": 27.98,
        "Filter_381": 27.98,
        "Filter_382": 28.0,
        "Filter_383": 27.98,
        "Filter_384": 28.0,
        "Filter_385": 27.99,
        "Filter_386": 27.99,
        "Filter_387": 27.98,
        "Filter_388": 28.0,
        "Filter_389": 27.98,
        "Filter_390": 28.0,
        "Filter_391": 27.99,
        "Filter_392": 27.98,
        "Filter_393": 28.0,
        "Filter_394": 27.99,
        "Filter_395": 27.98,
        "Filter_396": 28.0,
        "Filter_397": 27.98,
        "Filter_398": 27.97,
        "Filter_399": 27.99,
        "Filter_400": 28.0,
        "Filter_401": 28.0,
        "Filter_402": 27.99,
        "Filter_403": 28.0,
        "Filter_404": 28.0,
        "Filter_405": 28.0,
        "Filter_406": 27.99,
        "Filter_407": 27.99,
        "Filter_408": 28.0,
        "Filter_409": 28.0,
        "Filter_410": 28.0,
        "Filter_411": 28.0,
        "Filter_412": 28.0,
        "Filter_413": 28.0,
        "Filter_414": 27.99,
        "Filter_415": 27.99,
        "Filter_416": 28.0,
        "Filter_417": 27.99,
        "Filter_418": 27.99,
        "Filter_419": 28.0,
        "Filter_420": 27.99,
        "Filter_421": 28.0,
        "Filter_422": 28.0,
        "Filter_423": 27.99,
        "Filter_424": 27.98,
        "Filter_425": 28.0,
        "Filter_426": 28.0,
        "Filter_427": 27.98,
        "Filter_428": 28.0,
        "Filter_429": 28.0,
        "Filter_430": 27.99,
        "Filter_431": 28.0,
        "Filter_432": 27.98,
        "Filter_433": 28.0,
        "Filter_434": 28.0,
        "Filter_435": 27.98,
        "Filter_436": 27.99,
        "Filter_437": 27.98,
        "Filter_438": 27.98,
        "Filter_439": 27.95,
        "Filter_440": 28.0,
        "Filter_441": 27.97,
        "Filter_442": 27.99,
        "Filter_443": 27.98,
        "Filter_444": 28.0,
        "Filter_445": 27.98,
        "Filter_446": 28.0,
        "Filter_447": 28.0,
        "Filter_448": 28.0,
        "Filter_449": 27.95,
        "Filter_450": 28.0,
        "Filter_451": 27.98,
        "Filter_452": 28.0,
        "Filter_453": 28.0,
        "Filter_454": 27.98,
        "Filter_455": 28.0,
        "Filter_456": 28.0,
        "Filter_457": 27.99,
        "Filter_458": 28.0,
        "Filter_459": 27.99,
        "Filter_460": 28.0,
        "Filter_461": 27.98,
        "Filter_462": 28.0,
        "Filter_463": 28.0,
        "Filter_464": 27.95,
        "Filter_465": 27.99,
        "Filter_466": 27.99,
        "Filter_467": 28.0,
        "Filter_468": 28.0,
        "Filter_469": 28.0,
        "Filter_470": 27.99,
        "Filter_471": 28.0,
        "Filter_472": 27.99,
        "Filter_473": 27.99,
        "Filter_474": 28.0,
        "Filter_475": 27.98,
        "Filter_476": 27.98,
        "Filter_477": 28.0,
        "Filter_478": 28.0,
        "Filter_479": 28.0,
        "Filter_480": 27.99,
        "Filter_481": 28.0,
        "Filter_482": 28.0,
        "Filter_483": 28.0,
        "Filter_484": 27.99,
        "Filter_485": 27.99,
        "Filter_486": 28.0,
        "Filter_487": 28.0,
        "Filter_488": 28.0,
        "Filter_489": 27.97,
        "Filter_490": 28.0,
        "Filter_491": 27.99,
        "Filter_492": 28.0,
        "Filter_493": 27.99,
        "Filter_494": 28.0,
        "Filter_495": 27.98,
        "Filter_496": 27.97,
        "Filter_497": 27.99,
        "Filter_498": 28.0,
        "Filter_499": 28.0,
        "Filter_500": 28.0,
        "Filter_501": 27.97,
        "Filter_502": 27.98,
        "Filter_503": 27.99,
        "Filter_504": 28.0,
        "Filter_505": 27.99,
        "Filter_506": 28.0,
        "Filter_507": 27.95,
        "Filter_508": 28.0,
        "Filter_509": 28.0,
        "Filter_510": 27.98,
        "Filter_511": 28.0
    },
    "Layer_7_Conv2d_512to512": {
        "Filter_0": 14.0,
        "Filter_1": 14.0,
        "Filter_2": 14.0,
        "Filter_3": 14.0,
        "Filter_4": 14.0,
        "Filter_5": 14.0,
        "Filter_6": 14.0,
        "Filter_7": 14.0,
        "Filter_8": 14.0,
        "Filter_9": 14.0,
        "Filter_10": 14.0,
        "Filter_11": 14.0,
        "Filter_12": 14.0,
        "Filter_13": 14.0,
        "Filter_14": 14.0,
        "Filter_15": 14.0,
        "Filter_16": 14.0,
        "Filter_17": 14.0,
        "Filter_18": 14.0,
        "Filter_19": 14.0,
        "Filter_20": 14.0,
        "Filter_21": 14.0,
        "Filter_22": 14.0,
        "Filter_23": 14.0,
        "Filter_24": 14.0,
        "Filter_25": 14.0,
        "Filter_26": 14.0,
        "Filter_27": 14.0,
        "Filter_28": 14.0,
        "Filter_29": 14.0,
        "Filter_30": 14.0,
        "Filter_31": 14.0,
        "Filter_32": 14.0,
        "Filter_33": 14.0,
        "Filter_34": 14.0,
        "Filter_35": 14.0,
        "Filter_36": 14.0,
        "Filter_37": 14.0,
        "Filter_38": 14.0,
        "Filter_39": 14.0,
        "Filter_40": 14.0,
        "Filter_41": 14.0,
        "Filter_42": 14.0,
        "Filter_43": 14.0,
        "Filter_44": 14.0,
        "Filter_45": 14.0,
        "Filter_46": 14.0,
        "Filter_47": 14.0,
        "Filter_48": 14.0,
        "Filter_49": 14.0,
        "Filter_50": 14.0,
        "Filter_51": 14.0,
        "Filter_52": 14.0,
        "Filter_53": 14.0,
        "Filter_54": 13.99,
        "Filter_55": 14.0,
        "Filter_56": 14.0,
        "Filter_57": 14.0,
        "Filter_58": 14.0,
        "Filter_59": 14.0,
        "Filter_60": 14.0,
        "Filter_61": 14.0,
        "Filter_62": 14.0,
        "Filter_63": 14.0,
        "Filter_64": 13.99,
        "Filter_65": 14.0,
        "Filter_66": 14.0,
        "Filter_67": 14.0,
        "Filter_68": 14.0,
        "Filter_69": 14.0,
        "Filter_70": 14.0,
        "Filter_71": 14.0,
        "Filter_72": 14.0,
        "Filter_73": 14.0,
        "Filter_74": 13.99,
        "Filter_75": 14.0,
        "Filter_76": 14.0,
        "Filter_77": 14.0,
        "Filter_78": 14.0,
        "Filter_79": 14.0,
        "Filter_80": 14.0,
        "Filter_81": 14.0,
        "Filter_82": 14.0,
        "Filter_83": 14.0,
        "Filter_84": 14.0,
        "Filter_85": 14.0,
        "Filter_86": 14.0,
        "Filter_87": 13.99,
        "Filter_88": 14.0,
        "Filter_89": 13.99,
        "Filter_90": 14.0,
        "Filter_91": 14.0,
        "Filter_92": 14.0,
        "Filter_93": 14.0,
        "Filter_94": 14.0,
        "Filter_95": 14.0,
        "Filter_96": 14.0,
        "Filter_97": 14.0,
        "Filter_98": 14.0,
        "Filter_99": 14.0,
        "Filter_100": 14.0,
        "Filter_101": 14.0,
        "Filter_102": 14.0,
        "Filter_103": 14.0,
        "Filter_104": 14.0,
        "Filter_105": 14.0,
        "Filter_106": 14.0,
        "Filter_107": 14.0,
        "Filter_108": 14.0,
        "Filter_109": 14.0,
        "Filter_110": 14.0,
        "Filter_111": 14.0,
        "Filter_112": 14.0,
        "Filter_113": 14.0,
        "Filter_114": 14.0,
        "Filter_115": 14.0,
        "Filter_116": 14.0,
        "Filter_117": 14.0,
        "Filter_118": 14.0,
        "Filter_119": 14.0,
        "Filter_120": 14.0,
        "Filter_121": 14.0,
        "Filter_122": 14.0,
        "Filter_123": 14.0,
        "Filter_124": 14.0,
        "Filter_125": 14.0,
        "Filter_126": 14.0,
        "Filter_127": 14.0,
        "Filter_128": 14.0,
        "Filter_129": 14.0,
        "Filter_130": 14.0,
        "Filter_131": 14.0,
        "Filter_132": 14.0,
        "Filter_133": 14.0,
        "Filter_134": 14.0,
        "Filter_135": 14.0,
        "Filter_136": 14.0,
        "Filter_137": 14.0,
        "Filter_138": 14.0,
        "Filter_139": 13.99,
        "Filter_140": 14.0,
        "Filter_141": 14.0,
        "Filter_142": 14.0,
        "Filter_143": 14.0,
        "Filter_144": 14.0,
        "Filter_145": 14.0,
        "Filter_146": 14.0,
        "Filter_147": 13.99,
        "Filter_148": 14.0,
        "Filter_149": 14.0,
        "Filter_150": 14.0,
        "Filter_151": 14.0,
        "Filter_152": 14.0,
        "Filter_153": 14.0,
        "Filter_154": 14.0,
        "Filter_155": 14.0,
        "Filter_156": 14.0,
        "Filter_157": 14.0,
        "Filter_158": 13.99,
        "Filter_159": 14.0,
        "Filter_160": 14.0,
        "Filter_161": 14.0,
        "Filter_162": 14.0,
        "Filter_163": 14.0,
        "Filter_164": 14.0,
        "Filter_165": 14.0,
        "Filter_166": 14.0,
        "Filter_167": 14.0,
        "Filter_168": 14.0,
        "Filter_169": 14.0,
        "Filter_170": 13.99,
        "Filter_171": 14.0,
        "Filter_172": 14.0,
        "Filter_173": 13.99,
        "Filter_174": 14.0,
        "Filter_175": 14.0,
        "Filter_176": 14.0,
        "Filter_177": 14.0,
        "Filter_178": 14.0,
        "Filter_179": 14.0,
        "Filter_180": 14.0,
        "Filter_181": 14.0,
        "Filter_182": 14.0,
        "Filter_183": 14.0,
        "Filter_184": 14.0,
        "Filter_185": 14.0,
        "Filter_186": 14.0,
        "Filter_187": 14.0,
        "Filter_188": 13.99,
        "Filter_189": 14.0,
        "Filter_190": 14.0,
        "Filter_191": 14.0,
        "Filter_192": 14.0,
        "Filter_193": 14.0,
        "Filter_194": 14.0,
        "Filter_195": 14.0,
        "Filter_196": 14.0,
        "Filter_197": 14.0,
        "Filter_198": 14.0,
        "Filter_199": 14.0,
        "Filter_200": 14.0,
        "Filter_201": 14.0,
        "Filter_202": 14.0,
        "Filter_203": 14.0,
        "Filter_204": 14.0,
        "Filter_205": 14.0,
        "Filter_206": 14.0,
        "Filter_207": 14.0,
        "Filter_208": 14.0,
        "Filter_209": 14.0,
        "Filter_210": 14.0,
        "Filter_211": 14.0,
        "Filter_212": 14.0,
        "Filter_213": 14.0,
        "Filter_214": 14.0,
        "Filter_215": 14.0,
        "Filter_216": 14.0,
        "Filter_217": 14.0,
        "Filter_218": 14.0,
        "Filter_219": 14.0,
        "Filter_220": 14.0,
        "Filter_221": 14.0,
        "Filter_222": 14.0,
        "Filter_223": 13.99,
        "Filter_224": 14.0,
        "Filter_225": 14.0,
        "Filter_226": 14.0,
        "Filter_227": 14.0,
        "Filter_228": 14.0,
        "Filter_229": 14.0,
        "Filter_230": 14.0,
        "Filter_231": 14.0,
        "Filter_232": 14.0,
        "Filter_233": 14.0,
        "Filter_234": 14.0,
        "Filter_235": 13.99,
        "Filter_236": 14.0,
        "Filter_237": 14.0,
        "Filter_238": 14.0,
        "Filter_239": 14.0,
        "Filter_240": 14.0,
        "Filter_241": 14.0,
        "Filter_242": 14.0,
        "Filter_243": 14.0,
        "Filter_244": 14.0,
        "Filter_245": 14.0,
        "Filter_246": 14.0,
        "Filter_247": 14.0,
        "Filter_248": 13.99,
        "Filter_249": 14.0,
        "Filter_250": 14.0,
        "Filter_251": 13.99,
        "Filter_252": 14.0,
        "Filter_253": 13.99,
        "Filter_254": 14.0,
        "Filter_255": 14.0,
        "Filter_256": 14.0,
        "Filter_257": 14.0,
        "Filter_258": 14.0,
        "Filter_259": 14.0,
        "Filter_260": 14.0,
        "Filter_261": 14.0,
        "Filter_262": 13.99,
        "Filter_263": 14.0,
        "Filter_264": 14.0,
        "Filter_265": 14.0,
        "Filter_266": 14.0,
        "Filter_267": 14.0,
        "Filter_268": 14.0,
        "Filter_269": 14.0,
        "Filter_270": 14.0,
        "Filter_271": 14.0,
        "Filter_272": 14.0,
        "Filter_273": 14.0,
        "Filter_274": 14.0,
        "Filter_275": 14.0,
        "Filter_276": 14.0,
        "Filter_277": 14.0,
        "Filter_278": 14.0,
        "Filter_279": 14.0,
        "Filter_280": 14.0,
        "Filter_281": 13.99,
        "Filter_282": 14.0,
        "Filter_283": 14.0,
        "Filter_284": 14.0,
        "Filter_285": 14.0,
        "Filter_286": 14.0,
        "Filter_287": 14.0,
        "Filter_288": 14.0,
        "Filter_289": 14.0,
        "Filter_290": 14.0,
        "Filter_291": 14.0,
        "Filter_292": 14.0,
        "Filter_293": 14.0,
        "Filter_294": 14.0,
        "Filter_295": 13.99,
        "Filter_296": 14.0,
        "Filter_297": 14.0,
        "Filter_298": 14.0,
        "Filter_299": 14.0,
        "Filter_300": 14.0,
        "Filter_301": 13.99,
        "Filter_302": 14.0,
        "Filter_303": 14.0,
        "Filter_304": 14.0,
        "Filter_305": 14.0,
        "Filter_306": 14.0,
        "Filter_307": 14.0,
        "Filter_308": 14.0,
        "Filter_309": 14.0,
        "Filter_310": 14.0,
        "Filter_311": 14.0,
        "Filter_312": 14.0,
        "Filter_313": 14.0,
        "Filter_314": 14.0,
        "Filter_315": 14.0,
        "Filter_316": 14.0,
        "Filter_317": 14.0,
        "Filter_318": 14.0,
        "Filter_319": 13.99,
        "Filter_320": 14.0,
        "Filter_321": 14.0,
        "Filter_322": 14.0,
        "Filter_323": 14.0,
        "Filter_324": 14.0,
        "Filter_325": 14.0,
        "Filter_326": 14.0,
        "Filter_327": 14.0,
        "Filter_328": 14.0,
        "Filter_329": 14.0,
        "Filter_330": 14.0,
        "Filter_331": 14.0,
        "Filter_332": 14.0,
        "Filter_333": 13.99,
        "Filter_334": 14.0,
        "Filter_335": 14.0,
        "Filter_336": 14.0,
        "Filter_337": 14.0,
        "Filter_338": 14.0,
        "Filter_339": 14.0,
        "Filter_340": 14.0,
        "Filter_341": 14.0,
        "Filter_342": 14.0,
        "Filter_343": 14.0,
        "Filter_344": 14.0,
        "Filter_345": 14.0,
        "Filter_346": 14.0,
        "Filter_347": 14.0,
        "Filter_348": 14.0,
        "Filter_349": 14.0,
        "Filter_350": 14.0,
        "Filter_351": 14.0,
        "Filter_352": 14.0,
        "Filter_353": 14.0,
        "Filter_354": 14.0,
        "Filter_355": 14.0,
        "Filter_356": 14.0,
        "Filter_357": 14.0,
        "Filter_358": 14.0,
        "Filter_359": 14.0,
        "Filter_360": 14.0,
        "Filter_361": 14.0,
        "Filter_362": 14.0,
        "Filter_363": 14.0,
        "Filter_364": 14.0,
        "Filter_365": 14.0,
        "Filter_366": 14.0,
        "Filter_367": 14.0,
        "Filter_368": 13.99,
        "Filter_369": 14.0,
        "Filter_370": 14.0,
        "Filter_371": 14.0,
        "Filter_372": 14.0,
        "Filter_373": 14.0,
        "Filter_374": 13.99,
        "Filter_375": 14.0,
        "Filter_376": 14.0,
        "Filter_377": 14.0,
        "Filter_378": 14.0,
        "Filter_379": 14.0,
        "Filter_380": 14.0,
        "Filter_381": 13.99,
        "Filter_382": 14.0,
        "Filter_383": 14.0,
        "Filter_384": 14.0,
        "Filter_385": 14.0,
        "Filter_386": 14.0,
        "Filter_387": 14.0,
        "Filter_388": 14.0,
        "Filter_389": 14.0,
        "Filter_390": 14.0,
        "Filter_391": 13.99,
        "Filter_392": 14.0,
        "Filter_393": 14.0,
        "Filter_394": 14.0,
        "Filter_395": 13.99,
        "Filter_396": 14.0,
        "Filter_397": 14.0,
        "Filter_398": 14.0,
        "Filter_399": 14.0,
        "Filter_400": 14.0,
        "Filter_401": 14.0,
        "Filter_402": 14.0,
        "Filter_403": 13.99,
        "Filter_404": 14.0,
        "Filter_405": 14.0,
        "Filter_406": 14.0,
        "Filter_407": 14.0,
        "Filter_408": 14.0,
        "Filter_409": 14.0,
        "Filter_410": 14.0,
        "Filter_411": 14.0,
        "Filter_412": 14.0,
        "Filter_413": 14.0,
        "Filter_414": 14.0,
        "Filter_415": 14.0,
        "Filter_416": 14.0,
        "Filter_417": 14.0,
        "Filter_418": 14.0,
        "Filter_419": 14.0,
        "Filter_420": 14.0,
        "Filter_421": 14.0,
        "Filter_422": 14.0,
        "Filter_423": 14.0,
        "Filter_424": 13.99,
        "Filter_425": 14.0,
        "Filter_426": 14.0,
        "Filter_427": 14.0,
        "Filter_428": 14.0,
        "Filter_429": 14.0,
        "Filter_430": 14.0,
        "Filter_431": 14.0,
        "Filter_432": 14.0,
        "Filter_433": 14.0,
        "Filter_434": 14.0,
        "Filter_435": 14.0,
        "Filter_436": 14.0,
        "Filter_437": 14.0,
        "Filter_438": 14.0,
        "Filter_439": 14.0,
        "Filter_440": 14.0,
        "Filter_441": 14.0,
        "Filter_442": 14.0,
        "Filter_443": 14.0,
        "Filter_444": 13.99,
        "Filter_445": 14.0,
        "Filter_446": 14.0,
        "Filter_447": 14.0,
        "Filter_448": 14.0,
        "Filter_449": 13.99,
        "Filter_450": 14.0,
        "Filter_451": 14.0,
        "Filter_452": 14.0,
        "Filter_453": 14.0,
        "Filter_454": 14.0,
        "Filter_455": 14.0,
        "Filter_456": 14.0,
        "Filter_457": 14.0,
        "Filter_458": 14.0,
        "Filter_459": 14.0,
        "Filter_460": 14.0,
        "Filter_461": 14.0,
        "Filter_462": 14.0,
        "Filter_463": 14.0,
        "Filter_464": 14.0,
        "Filter_465": 14.0,
        "Filter_466": 14.0,
        "Filter_467": 14.0,
        "Filter_468": 14.0,
        "Filter_469": 14.0,
        "Filter_470": 14.0,
        "Filter_471": 14.0,
        "Filter_472": 14.0,
        "Filter_473": 14.0,
        "Filter_474": 14.0,
        "Filter_475": 14.0,
        "Filter_476": 14.0,
        "Filter_477": 14.0,
        "Filter_478": 14.0,
        "Filter_479": 14.0,
        "Filter_480": 14.0,
        "Filter_481": 14.0,
        "Filter_482": 14.0,
        "Filter_483": 14.0,
        "Filter_484": 14.0,
        "Filter_485": 14.0,
        "Filter_486": 14.0,
        "Filter_487": 13.99,
        "Filter_488": 14.0,
        "Filter_489": 14.0,
        "Filter_490": 14.0,
        "Filter_491": 13.99,
        "Filter_492": 14.0,
        "Filter_493": 14.0,
        "Filter_494": 14.0,
        "Filter_495": 14.0,
        "Filter_496": 14.0,
        "Filter_497": 14.0,
        "Filter_498": 14.0,
        "Filter_499": 14.0,
        "Filter_500": 14.0,
        "Filter_501": 14.0,
        "Filter_502": 14.0,
        "Filter_503": 14.0,
        "Filter_504": 14.0,
        "Filter_505": 14.0,
        "Filter_506": 14.0,
        "Filter_507": 14.0,
        "Filter_508": 14.0,
        "Filter_509": 14.0,
        "Filter_510": 14.0,
        "Filter_511": 14.0
    },
    "Layer_8_Conv2d_512to512": {
        "Filter_0": 14.0,
        "Filter_1": 14.0,
        "Filter_2": 14.0,
        "Filter_3": 14.0,
        "Filter_4": 14.0,
        "Filter_5": 14.0,
        "Filter_6": 14.0,
        "Filter_7": 14.0,
        "Filter_8": 14.0,
        "Filter_9": 14.0,
        "Filter_10": 14.0,
        "Filter_11": 14.0,
        "Filter_12": 14.0,
        "Filter_13": 14.0,
        "Filter_14": 14.0,
        "Filter_15": 14.0,
        "Filter_16": 14.0,
        "Filter_17": 14.0,
        "Filter_18": 14.0,
        "Filter_19": 14.0,
        "Filter_20": 14.0,
        "Filter_21": 14.0,
        "Filter_22": 14.0,
        "Filter_23": 14.0,
        "Filter_24": 14.0,
        "Filter_25": 14.0,
        "Filter_26": 13.99,
        "Filter_27": 14.0,
        "Filter_28": 14.0,
        "Filter_29": 14.0,
        "Filter_30": 14.0,
        "Filter_31": 14.0,
        "Filter_32": 14.0,
        "Filter_33": 14.0,
        "Filter_34": 14.0,
        "Filter_35": 14.0,
        "Filter_36": 14.0,
        "Filter_37": 14.0,
        "Filter_38": 14.0,
        "Filter_39": 14.0,
        "Filter_40": 14.0,
        "Filter_41": 14.0,
        "Filter_42": 14.0,
        "Filter_43": 14.0,
        "Filter_44": 14.0,
        "Filter_45": 14.0,
        "Filter_46": 14.0,
        "Filter_47": 14.0,
        "Filter_48": 14.0,
        "Filter_49": 14.0,
        "Filter_50": 13.99,
        "Filter_51": 14.0,
        "Filter_52": 14.0,
        "Filter_53": 14.0,
        "Filter_54": 14.0,
        "Filter_55": 14.0,
        "Filter_56": 14.0,
        "Filter_57": 14.0,
        "Filter_58": 13.99,
        "Filter_59": 14.0,
        "Filter_60": 14.0,
        "Filter_61": 14.0,
        "Filter_62": 14.0,
        "Filter_63": 13.99,
        "Filter_64": 14.0,
        "Filter_65": 14.0,
        "Filter_66": 13.99,
        "Filter_67": 14.0,
        "Filter_68": 14.0,
        "Filter_69": 14.0,
        "Filter_70": 14.0,
        "Filter_71": 14.0,
        "Filter_72": 14.0,
        "Filter_73": 14.0,
        "Filter_74": 14.0,
        "Filter_75": 14.0,
        "Filter_76": 14.0,
        "Filter_77": 14.0,
        "Filter_78": 14.0,
        "Filter_79": 14.0,
        "Filter_80": 13.99,
        "Filter_81": 14.0,
        "Filter_82": 14.0,
        "Filter_83": 14.0,
        "Filter_84": 14.0,
        "Filter_85": 14.0,
        "Filter_86": 14.0,
        "Filter_87": 13.99,
        "Filter_88": 14.0,
        "Filter_89": 14.0,
        "Filter_90": 14.0,
        "Filter_91": 14.0,
        "Filter_92": 14.0,
        "Filter_93": 14.0,
        "Filter_94": 14.0,
        "Filter_95": 14.0,
        "Filter_96": 14.0,
        "Filter_97": 14.0,
        "Filter_98": 14.0,
        "Filter_99": 14.0,
        "Filter_100": 14.0,
        "Filter_101": 13.99,
        "Filter_102": 14.0,
        "Filter_103": 14.0,
        "Filter_104": 14.0,
        "Filter_105": 14.0,
        "Filter_106": 14.0,
        "Filter_107": 13.99,
        "Filter_108": 14.0,
        "Filter_109": 14.0,
        "Filter_110": 14.0,
        "Filter_111": 14.0,
        "Filter_112": 14.0,
        "Filter_113": 14.0,
        "Filter_114": 14.0,
        "Filter_115": 13.99,
        "Filter_116": 14.0,
        "Filter_117": 14.0,
        "Filter_118": 14.0,
        "Filter_119": 14.0,
        "Filter_120": 14.0,
        "Filter_121": 14.0,
        "Filter_122": 14.0,
        "Filter_123": 14.0,
        "Filter_124": 14.0,
        "Filter_125": 14.0,
        "Filter_126": 14.0,
        "Filter_127": 14.0,
        "Filter_128": 13.99,
        "Filter_129": 14.0,
        "Filter_130": 14.0,
        "Filter_131": 14.0,
        "Filter_132": 14.0,
        "Filter_133": 14.0,
        "Filter_134": 14.0,
        "Filter_135": 14.0,
        "Filter_136": 14.0,
        "Filter_137": 14.0,
        "Filter_138": 14.0,
        "Filter_139": 14.0,
        "Filter_140": 14.0,
        "Filter_141": 14.0,
        "Filter_142": 14.0,
        "Filter_143": 14.0,
        "Filter_144": 14.0,
        "Filter_145": 14.0,
        "Filter_146": 14.0,
        "Filter_147": 14.0,
        "Filter_148": 14.0,
        "Filter_149": 14.0,
        "Filter_150": 14.0,
        "Filter_151": 14.0,
        "Filter_152": 14.0,
        "Filter_153": 14.0,
        "Filter_154": 14.0,
        "Filter_155": 14.0,
        "Filter_156": 13.99,
        "Filter_157": 14.0,
        "Filter_158": 14.0,
        "Filter_159": 13.99,
        "Filter_160": 14.0,
        "Filter_161": 14.0,
        "Filter_162": 14.0,
        "Filter_163": 14.0,
        "Filter_164": 14.0,
        "Filter_165": 14.0,
        "Filter_166": 14.0,
        "Filter_167": 14.0,
        "Filter_168": 14.0,
        "Filter_169": 14.0,
        "Filter_170": 14.0,
        "Filter_171": 14.0,
        "Filter_172": 14.0,
        "Filter_173": 14.0,
        "Filter_174": 14.0,
        "Filter_175": 14.0,
        "Filter_176": 14.0,
        "Filter_177": 14.0,
        "Filter_178": 13.99,
        "Filter_179": 14.0,
        "Filter_180": 14.0,
        "Filter_181": 14.0,
        "Filter_182": 14.0,
        "Filter_183": 14.0,
        "Filter_184": 14.0,
        "Filter_185": 14.0,
        "Filter_186": 14.0,
        "Filter_187": 13.99,
        "Filter_188": 14.0,
        "Filter_189": 13.99,
        "Filter_190": 14.0,
        "Filter_191": 14.0,
        "Filter_192": 14.0,
        "Filter_193": 14.0,
        "Filter_194": 14.0,
        "Filter_195": 14.0,
        "Filter_196": 14.0,
        "Filter_197": 13.99,
        "Filter_198": 14.0,
        "Filter_199": 14.0,
        "Filter_200": 14.0,
        "Filter_201": 14.0,
        "Filter_202": 14.0,
        "Filter_203": 14.0,
        "Filter_204": 14.0,
        "Filter_205": 13.99,
        "Filter_206": 14.0,
        "Filter_207": 14.0,
        "Filter_208": 13.99,
        "Filter_209": 14.0,
        "Filter_210": 14.0,
        "Filter_211": 14.0,
        "Filter_212": 14.0,
        "Filter_213": 14.0,
        "Filter_214": 14.0,
        "Filter_215": 14.0,
        "Filter_216": 14.0,
        "Filter_217": 14.0,
        "Filter_218": 14.0,
        "Filter_219": 14.0,
        "Filter_220": 14.0,
        "Filter_221": 14.0,
        "Filter_222": 14.0,
        "Filter_223": 14.0,
        "Filter_224": 14.0,
        "Filter_225": 14.0,
        "Filter_226": 14.0,
        "Filter_227": 14.0,
        "Filter_228": 14.0,
        "Filter_229": 14.0,
        "Filter_230": 14.0,
        "Filter_231": 14.0,
        "Filter_232": 14.0,
        "Filter_233": 14.0,
        "Filter_234": 14.0,
        "Filter_235": 14.0,
        "Filter_236": 14.0,
        "Filter_237": 14.0,
        "Filter_238": 14.0,
        "Filter_239": 14.0,
        "Filter_240": 13.99,
        "Filter_241": 14.0,
        "Filter_242": 14.0,
        "Filter_243": 14.0,
        "Filter_244": 14.0,
        "Filter_245": 14.0,
        "Filter_246": 14.0,
        "Filter_247": 14.0,
        "Filter_248": 14.0,
        "Filter_249": 13.98,
        "Filter_250": 14.0,
        "Filter_251": 14.0,
        "Filter_252": 14.0,
        "Filter_253": 14.0,
        "Filter_254": 14.0,
        "Filter_255": 14.0,
        "Filter_256": 14.0,
        "Filter_257": 13.98,
        "Filter_258": 14.0,
        "Filter_259": 14.0,
        "Filter_260": 14.0,
        "Filter_261": 14.0,
        "Filter_262": 14.0,
        "Filter_263": 14.0,
        "Filter_264": 14.0,
        "Filter_265": 14.0,
        "Filter_266": 14.0,
        "Filter_267": 14.0,
        "Filter_268": 14.0,
        "Filter_269": 14.0,
        "Filter_270": 14.0,
        "Filter_271": 14.0,
        "Filter_272": 14.0,
        "Filter_273": 14.0,
        "Filter_274": 14.0,
        "Filter_275": 14.0,
        "Filter_276": 14.0,
        "Filter_277": 14.0,
        "Filter_278": 13.99,
        "Filter_279": 13.99,
        "Filter_280": 13.99,
        "Filter_281": 14.0,
        "Filter_282": 14.0,
        "Filter_283": 13.99,
        "Filter_284": 13.99,
        "Filter_285": 14.0,
        "Filter_286": 14.0,
        "Filter_287": 14.0,
        "Filter_288": 14.0,
        "Filter_289": 14.0,
        "Filter_290": 13.99,
        "Filter_291": 14.0,
        "Filter_292": 14.0,
        "Filter_293": 14.0,
        "Filter_294": 14.0,
        "Filter_295": 13.99,
        "Filter_296": 14.0,
        "Filter_297": 14.0,
        "Filter_298": 14.0,
        "Filter_299": 14.0,
        "Filter_300": 14.0,
        "Filter_301": 13.99,
        "Filter_302": 14.0,
        "Filter_303": 14.0,
        "Filter_304": 14.0,
        "Filter_305": 14.0,
        "Filter_306": 14.0,
        "Filter_307": 13.99,
        "Filter_308": 14.0,
        "Filter_309": 13.99,
        "Filter_310": 14.0,
        "Filter_311": 14.0,
        "Filter_312": 14.0,
        "Filter_313": 13.99,
        "Filter_314": 14.0,
        "Filter_315": 14.0,
        "Filter_316": 14.0,
        "Filter_317": 14.0,
        "Filter_318": 14.0,
        "Filter_319": 14.0,
        "Filter_320": 14.0,
        "Filter_321": 13.98,
        "Filter_322": 14.0,
        "Filter_323": 14.0,
        "Filter_324": 14.0,
        "Filter_325": 14.0,
        "Filter_326": 14.0,
        "Filter_327": 14.0,
        "Filter_328": 14.0,
        "Filter_329": 13.99,
        "Filter_330": 13.99,
        "Filter_331": 14.0,
        "Filter_332": 14.0,
        "Filter_333": 13.99,
        "Filter_334": 13.99,
        "Filter_335": 14.0,
        "Filter_336": 14.0,
        "Filter_337": 14.0,
        "Filter_338": 14.0,
        "Filter_339": 14.0,
        "Filter_340": 14.0,
        "Filter_341": 14.0,
        "Filter_342": 14.0,
        "Filter_343": 14.0,
        "Filter_344": 14.0,
        "Filter_345": 14.0,
        "Filter_346": 14.0,
        "Filter_347": 14.0,
        "Filter_348": 14.0,
        "Filter_349": 14.0,
        "Filter_350": 14.0,
        "Filter_351": 14.0,
        "Filter_352": 13.99,
        "Filter_353": 14.0,
        "Filter_354": 14.0,
        "Filter_355": 14.0,
        "Filter_356": 14.0,
        "Filter_357": 14.0,
        "Filter_358": 14.0,
        "Filter_359": 14.0,
        "Filter_360": 13.99,
        "Filter_361": 14.0,
        "Filter_362": 14.0,
        "Filter_363": 14.0,
        "Filter_364": 14.0,
        "Filter_365": 14.0,
        "Filter_366": 14.0,
        "Filter_367": 14.0,
        "Filter_368": 14.0,
        "Filter_369": 13.99,
        "Filter_370": 14.0,
        "Filter_371": 14.0,
        "Filter_372": 13.99,
        "Filter_373": 14.0,
        "Filter_374": 14.0,
        "Filter_375": 14.0,
        "Filter_376": 14.0,
        "Filter_377": 14.0,
        "Filter_378": 14.0,
        "Filter_379": 14.0,
        "Filter_380": 13.99,
        "Filter_381": 14.0,
        "Filter_382": 14.0,
        "Filter_383": 14.0,
        "Filter_384": 13.99,
        "Filter_385": 13.99,
        "Filter_386": 14.0,
        "Filter_387": 14.0,
        "Filter_388": 14.0,
        "Filter_389": 14.0,
        "Filter_390": 13.99,
        "Filter_391": 14.0,
        "Filter_392": 14.0,
        "Filter_393": 14.0,
        "Filter_394": 14.0,
        "Filter_395": 14.0,
        "Filter_396": 14.0,
        "Filter_397": 14.0,
        "Filter_398": 14.0,
        "Filter_399": 14.0,
        "Filter_400": 14.0,
        "Filter_401": 14.0,
        "Filter_402": 14.0,
        "Filter_403": 14.0,
        "Filter_404": 14.0,
        "Filter_405": 14.0,
        "Filter_406": 14.0,
        "Filter_407": 14.0,
        "Filter_408": 14.0,
        "Filter_409": 13.98,
        "Filter_410": 14.0,
        "Filter_411": 14.0,
        "Filter_412": 13.99,
        "Filter_413": 14.0,
        "Filter_414": 14.0,
        "Filter_415": 14.0,
        "Filter_416": 14.0,
        "Filter_417": 14.0,
        "Filter_418": 14.0,
        "Filter_419": 13.99,
        "Filter_420": 14.0,
        "Filter_421": 14.0,
        "Filter_422": 14.0,
        "Filter_423": 14.0,
        "Filter_424": 14.0,
        "Filter_425": 14.0,
        "Filter_426": 14.0,
        "Filter_427": 14.0,
        "Filter_428": 14.0,
        "Filter_429": 14.0,
        "Filter_430": 14.0,
        "Filter_431": 14.0,
        "Filter_432": 14.0,
        "Filter_433": 14.0,
        "Filter_434": 14.0,
        "Filter_435": 14.0,
        "Filter_436": 14.0,
        "Filter_437": 14.0,
        "Filter_438": 14.0,
        "Filter_439": 14.0,
        "Filter_440": 13.99,
        "Filter_441": 14.0,
        "Filter_442": 14.0,
        "Filter_443": 14.0,
        "Filter_444": 14.0,
        "Filter_445": 14.0,
        "Filter_446": 14.0,
        "Filter_447": 14.0,
        "Filter_448": 14.0,
        "Filter_449": 14.0,
        "Filter_450": 14.0,
        "Filter_451": 14.0,
        "Filter_452": 14.0,
        "Filter_453": 14.0,
        "Filter_454": 14.0,
        "Filter_455": 14.0,
        "Filter_456": 14.0,
        "Filter_457": 14.0,
        "Filter_458": 14.0,
        "Filter_459": 13.99,
        "Filter_460": 14.0,
        "Filter_461": 14.0,
        "Filter_462": 14.0,
        "Filter_463": 14.0,
        "Filter_464": 14.0,
        "Filter_465": 14.0,
        "Filter_466": 14.0,
        "Filter_467": 14.0,
        "Filter_468": 13.99,
        "Filter_469": 14.0,
        "Filter_470": 14.0,
        "Filter_471": 13.99,
        "Filter_472": 13.99,
        "Filter_473": 14.0,
        "Filter_474": 13.99,
        "Filter_475": 14.0,
        "Filter_476": 14.0,
        "Filter_477": 14.0,
        "Filter_478": 14.0,
        "Filter_479": 13.99,
        "Filter_480": 14.0,
        "Filter_481": 14.0,
        "Filter_482": 14.0,
        "Filter_483": 14.0,
        "Filter_484": 14.0,
        "Filter_485": 14.0,
        "Filter_486": 14.0,
        "Filter_487": 13.99,
        "Filter_488": 14.0,
        "Filter_489": 14.0,
        "Filter_490": 14.0,
        "Filter_491": 14.0,
        "Filter_492": 14.0,
        "Filter_493": 14.0,
        "Filter_494": 14.0,
        "Filter_495": 14.0,
        "Filter_496": 14.0,
        "Filter_497": 14.0,
        "Filter_498": 14.0,
        "Filter_499": 14.0,
        "Filter_500": 14.0,
        "Filter_501": 14.0,
        "Filter_502": 14.0,
        "Filter_503": 14.0,
        "Filter_504": 13.99,
        "Filter_505": 14.0,
        "Filter_506": 13.99,
        "Filter_507": 14.0,
        "Filter_508": 14.0,
        "Filter_509": 14.0,
        "Filter_510": 14.0,
        "Filter_511": 14.0
    }
}